[
 {
   "objectname": "Android: Netrunner",
   "objectid": 124742,
   "rating": 0,
   "numplays": null,
   "own": 1,
   "collid": 21089692,
   "baverage": 7.78207,
   "average": 7.96113,
   "avgweight": 3.3521,
   "rank": 34,
   "numowned": 33807,
   "originalname": "Android: Netrunner",
   "minplayers": 2,
   "maxplayers": 2,
   "playingtime": 45,
   "maxplaytime": 45,
   "minplaytime": 45,
   "yearpublished": 2012,
   "bggrecplayers": "2",
   "bggbestplayers": "2",
   "bggrecagerange": "12+"
 },
 {
   "objectname": "Bananagrams",
   "objectid": 27225,
   "rating": 0,
   "numplays": null,
   "own": 1,
   "collid": 12839323,
   "baverage": 6.17583,
   "average": 6.34859,
   "avgweight": 1.3722,
   "rank": 1493,
   "numowned": 9819,
   "originalname": "Bananagrams",
   "minplayers": 1,
   "maxplayers": 8,
   "playingtime": 15,
   "maxplaytime": 15,
   "minplaytime": 15,
   "yearpublished": 2006,
   "bggrecplayers": "2,3,4,5,6",
   "bggbestplayers": "3,4,5",
   "bggrecagerange": "8+"
 },
 {
   "objectname": "Captain Sonar",
   "objectid": 171131,
   "rating": 8,
   "numplays": 1,
   "own": 0,
   "collid": 40815668,
   "baverage": 7.44078,
   "average": 7.77577,
   "avgweight": 2.0636,
   "rank": 92,
   "numowned": 9385,
   "originalname": "Captain Sonar",
   "minplayers": 2,
   "maxplayers": 8,
   "playingtime": 60,
   "maxplaytime": 60,
   "minplaytime": 45,
   "yearpublished": 2016,
   "bggrecplayers": "4,6,7,8",
   "bggbestplayers": "8",
   "bggrecagerange": "12+"
 },
 {
   "objectname": "Carcassonne",
   "objectid": 822,
   "rating": 0,
   "numplays": null,
   "own": 1,
   "collid": 12839326,
   "baverage": 7.33206,
   "average": 7.43327,
   "avgweight": 1.9344,
   "rank": 131,
   "numowned": 100509,
   "originalname": "Carcassonne",
   "minplayers": 2,
   "maxplayers": 5,
   "playingtime": 45,
   "maxplaytime": 45,
   "minplaytime": 30,
   "yearpublished": 2000,
   "bggrecplayers": "2,3,4,5",
   "bggbestplayers": "2",
   "bggrecagerange": "8+"
 },
 {
   "objectname": "Codenames",
   "objectid": 178900,
   "rating": 10,
   "numplays": 7,
   "own": 1,
   "collid": 34334574,
   "baverage": 7.74595,
   "average": 7.84276,
   "avgweight": 1.3505,
   "rank": 35,
   "numowned": 56674,
   "originalname": "Codenames",
   "minplayers": 2,
   "maxplayers": 8,
   "playingtime": 15,
   "maxplaytime": 15,
   "minplaytime": 15,
   "yearpublished": 2015,
   "bggrecplayers": "4,5,6,7,8",
   "bggbestplayers": "6,8",
   "bggrecagerange": "10+"
 },
 {
   "objectname": "Dead of Winter: A Crossroads Game",
   "objectid": 150376,
   "rating": 6,
   "numplays": 1,
   "own": 0,
   "collid": 34334643,
   "baverage": 7.65414,
   "average": 7.8005,
   "avgweight": 3.0009,
   "rank": 51,
   "numowned": 35875,
   "originalname": "Dead of Winter: A Crossroads Game",
   "minplayers": 2,
   "maxplayers": 5,
   "playingtime": 210,
   "maxplaytime": 210,
   "minplaytime": 45,
   "yearpublished": 2014,
   "bggrecplayers": "3,4,5",
   "bggbestplayers": "4",
   "bggrecagerange": "12+"
 },
 {
   "objectname": "Gloom",
   "objectid": 12692,
   "rating": 6,
   "numplays": 5,
   "own": 0,
   "collid": 34334626,
   "baverage": 6.22096,
   "average": 6.37213,
   "avgweight": 1.6421,
   "rank": 1386,
   "numowned": 19218,
   "originalname": "Gloom",
   "minplayers": 2,
   "maxplayers": 5,
   "playingtime": 60,
   "maxplaytime": 60,
   "minplaytime": 60,
   "yearpublished": 2005,
   "bggrecplayers": "2,3,4",
   "bggbestplayers": "4",
   "bggrecagerange": "10+"
 },
 {
   "objectname": "Jaipur",
   "objectid": 54043,
   "rating": 0,
   "numplays": null,
   "own": 1,
   "collid": 21089686,
   "baverage": 7.41872,
   "average": 7.54259,
   "avgweight": 1.524,
   "rank": 96,
   "numowned": 29241,
   "originalname": "Jaipur",
   "minplayers": 2,
   "maxplayers": 2,
   "playingtime": 30,
   "maxplaytime": 30,
   "minplaytime": 30,
   "yearpublished": 2009,
   "bggrecplayers": "2",
   "bggbestplayers": "2",
   "bggrecagerange": "8+"
 },
 {
   "objectname": "Letters from Whitechapel",
   "objectid": 59959,
   "rating": 8,
   "numplays": null,
   "own": 1,
   "collid": 34334611,
   "baverage": 7.25368,
   "average": 7.47694,
   "avgweight": 2.6858,
   "rank": 163,
   "numowned": 13338,
   "originalname": "Letters from Whitechapel",
   "minplayers": 2,
   "maxplayers": 6,
   "playingtime": 120,
   "maxplaytime": 120,
   "minplaytime": 120,
   "yearpublished": 2011,
   "bggrecplayers": "2,3,4,5,6",
   "bggbestplayers": "2",
   "bggrecagerange": "12+"
 },
 {
   "objectname": "Libertalia",
   "objectid": 125618,
   "rating": 7,
   "numplays": 1,
   "own": 0,
   "collid": 38358496,
   "baverage": 7.07245,
   "average": 7.25273,
   "avgweight": 2.23,
   "rank": 280,
   "numowned": 11498,
   "originalname": "Libertalia",
   "minplayers": 2,
   "maxplayers": 6,
   "playingtime": 45,
   "maxplaytime": 45,
   "minplaytime": 45,
   "yearpublished": 2012,
   "bggrecplayers": "3,4,5,6",
   "bggbestplayers": "4",
   "bggrecagerange": "10+"
 },
 {
   "objectname": "Pandemic",
   "objectid": 30549,
   "rating": 0,
   "numplays": null,
   "own": 1,
   "collid": 12839321,
   "baverage": 7.57444,
   "average": 7.66473,
   "avgweight": 2.4291,
   "rank": 65,
   "numowned": 98457,
   "originalname": "Pandemic",
   "minplayers": 2,
   "maxplayers": 4,
   "playingtime": 45,
   "maxplaytime": 45,
   "minplaytime": 45,
   "yearpublished": 2008,
   "bggrecplayers": "1,2,3,4",
   "bggbestplayers": "4",
   "bggrecagerange": "10+"
 },
 {
   "objectname": "Pandemic: On the Brink",
   "objectid": 40849,
   "rating": 7,
   "numplays": 1,
   "own": 0,
   "collid": 38358508,
   "baverage": 7.87519,
   "average": 8.09853,
   "avgweight": 2.6458,
   "rank": 0,
   "numowned": 33534,
   "originalname": "Pandemic: On the Brink",
   "minplayers": 2,
   "maxplayers": 5,
   "playingtime": 45,
   "maxplaytime": 45,
   "minplaytime": 45,
   "yearpublished": 2009,
   "bggrecplayers": "1,2,3,4,5",
   "bggbestplayers": "4",
   "bggrecagerange": "10+"
 },
 {
   "objectname": "Puerto Rico",
   "objectid": 3076,
   "rating": 0,
   "numplays": null,
   "own": 1,
   "collid": 16783007,
   "baverage": 7.96725,
   "average": 8.07699,
   "avgweight": 3.2944,
   "rank": 14,
   "numowned": 57747,
   "originalname": "Puerto Rico",
   "minplayers": 2,
   "maxplayers": 5,
   "playingtime": 150,
   "maxplaytime": 150,
   "minplaytime": 90,
   "yearpublished": 2002,
   "bggrecplayers": "2,3,4,5",
   "bggbestplayers": "4",
   "bggrecagerange": "12+"
 },
 {
   "objectname": "The Resistance: Avalon",
   "objectid": 128882,
   "rating": 8,
   "numplays": null,
   "own": 1,
   "collid": 35000559,
   "baverage": 7.52278,
   "average": 7.69358,
   "avgweight": 1.7816,
   "rank": 74,
   "numowned": 25078,
   "originalname": "The Resistance: Avalon",
   "minplayers": 5,
   "maxplayers": 10,
   "playingtime": 30,
   "maxplaytime": 30,
   "minplaytime": 30,
   "yearpublished": 2012,
   "bggrecplayers": "5,6,7,8,9,10",
   "bggbestplayers": "7,8",
   "bggrecagerange": "12+"
 },
 {
   "objectname": "Star Wars: Rebellion",
   "objectid": 187645,
   "rating": 0,
   "numplays": null,
   "own": 0,
   "collid": 38358949,
   "baverage": 8.16109,
   "average": 8.50797,
   "avgweight": 3.5838,
   "rank": 5,
   "numowned": 17175,
   "originalname": "Star Wars: Rebellion",
   "minplayers": 2,
   "maxplayers": 4,
   "playingtime": 240,
   "maxplaytime": 240,
   "minplaytime": 180,
   "yearpublished": 2016,
   "bggrecplayers": "2,4",
   "bggbestplayers": "2",
   "bggrecagerange": "12+"
 },
 {
   "objectname": "Terra Mystica",
   "objectid": 120677,
   "rating": 0,
   "numplays": null,
   "own": 0,
   "collid": 38358947,
   "baverage": 8.13628,
   "average": 8.28005,
   "avgweight": 3.946,
   "rank": 7,
   "numowned": 30391,
   "originalname": "Terra Mystica",
   "minplayers": 2,
   "maxplayers": 5,
   "playingtime": 150,
   "maxplaytime": 150,
   "minplaytime": 60,
   "yearpublished": 2012,
   "bggrecplayers": "2,3,4,5",
   "bggbestplayers": "4",
   "bggrecagerange": "12+"
 },
 {
   "objectname": "Ticket to Ride: Maarklin",
   "objectid": 21348,
   "rating": 0,
   "numplays": null,
   "own": 1,
   "collid": 12839320,
   "baverage": 7.16936,
   "average": 7.41372,
   "avgweight": 2.2416,
   "rank": 212,
   "numowned": 9671,
   "originalname": "Ticket to Ride: Märklin",
   "minplayers": 2,
   "maxplayers": 5,
   "playingtime": 60,
   "maxplaytime": 60,
   "minplaytime": 30,
   "yearpublished": 2006,
   "bggrecplayers": "2,3,4,5",
   "bggbestplayers": "4",
   "bggrecagerange": "8+"
 },
 {
   "objectname": "Twilight Struggle",
   "objectid": 12333,
   "rating": 8,
   "numplays": 1,
   "own": 0,
   "collid": 34999374,
   "baverage": 8.214,
   "average": 8.35441,
   "avgweight": 3.5407,
   "rank": 4,
   "numowned": 39913,
   "originalname": "Twilight Struggle",
   "minplayers": 2,
   "maxplayers": 2,
   "playingtime": 180,
   "maxplaytime": 180,
   "minplaytime": 120,
   "yearpublished": 2005,
   "bggrecplayers": "2",
   "bggbestplayers": "2",
   "bggrecagerange": "14+"
 },
 {
   "objectname": "Tzolk'in: The Mayan Calendar",
   "objectid": 126163,
   "rating": 7,
   "numplays": 1,
   "own": 0,
   "collid": 38358502,
   "baverage": 7.79056,
   "average": 7.93856,
   "avgweight": 3.63,
   "rank": 32,
   "numowned": 22226,
   "originalname": "Tzolk'in: The Mayan Calendar",
   "minplayers": 2,
   "maxplayers": 4,
   "playingtime": 90,
   "maxplaytime": 90,
   "minplaytime": 90,
   "yearpublished": 2012,
   "bggrecplayers": "2,3,4",
   "bggbestplayers": "4",
   "bggrecagerange": "12+"
 }
]